pkm_main/__init__.py
pkm_main/__main__.py
pkm_main/__version__.py
pkm_main/_vendor/.gitignore
pkm_main/app/__init__.py
pkm_main/app/relaxed_poetry.py
pkm_main/app/relaxed_poetry_updater.py
pkm_main/config/__init__.py
pkm_main/config/config.py
pkm_main/config/config_source.py
pkm_main/config/dict_config_source.py
pkm_main/config/file_config_source.py
pkm_main/config/source.py
pkm_main/console/__init__.py
pkm_main/console/application.py
pkm_main/console/command_loader.py
pkm_main/console/commands/__init__.py
pkm_main/console/commands/about.py
pkm_main/console/commands/build.py
pkm_main/console/commands/cache/__init__.py
pkm_main/console/commands/cache/clear.py
pkm_main/console/commands/cache/list.py
pkm_main/console/commands/check.py
pkm_main/console/commands/command.py
pkm_main/console/commands/config.py
pkm_main/console/commands/debug/__init__.py
pkm_main/console/commands/debug/info.py
pkm_main/console/commands/debug/resolve.py
pkm_main/console/commands/env/__init__.py
pkm_main/console/commands/env/info.py
pkm_main/console/commands/env/list.py
pkm_main/console/commands/env/remove.py
pkm_main/console/commands/env/use.py
pkm_main/console/commands/env_command.py
pkm_main/console/commands/export.py
pkm_main/console/commands/init.py
pkm_main/console/commands/install.py
pkm_main/console/commands/installer_command.py
pkm_main/console/commands/lock.py
pkm_main/console/commands/new.py
pkm_main/console/commands/plugin/__init__.py
pkm_main/console/commands/plugin/add.py
pkm_main/console/commands/plugin/remove.py
pkm_main/console/commands/plugin/show.py
pkm_main/console/commands/publish.py
pkm_main/console/commands/remove.py
pkm_main/console/commands/run.py
pkm_main/console/commands/search.py
pkm_main/console/commands/self/__init__.py
pkm_main/console/commands/self/update.py
pkm_main/console/commands/shell.py
pkm_main/console/commands/show.py
pkm_main/console/commands/source/__init__.py
pkm_main/console/commands/source/add.py
pkm_main/console/commands/source/remove.py
pkm_main-0.2.2.dist-info/entry_points.txt
pkm_main-0.2.2.dist-info/WHEEL
pkm_main-0.2.2.dist-info/METADATA
pkm_main-0.2.2.dist-info/RECORD
