Metadata-Version: 2.1
Name: pkm-main
Version: 0.2.2
Summary: Fork of Poetry (Python dependency management and packaging tool), attempts to be faster and less strict.
Home-page: https://github.com/bennylut/relaxed-poetry
License: MIT
Keywords: packaging,dependency,poetry,relaxed-poetry
Author: bennylut
Requires-Python: >=3.6,<4.0
Classifier: License :: OSI Approved :: MIT License
Classifier: Programming Language :: Python :: 3
Classifier: Programming Language :: Python :: 3.6
Classifier: Programming Language :: Python :: 3.7
Classifier: Programming Language :: Python :: 3.8
Classifier: Programming Language :: Python :: 3.9
Classifier: Programming Language :: Python :: 3.10
Classifier: Topic :: Software Development :: Build Tools
Classifier: Topic :: Software Development :: Libraries :: Python Modules
Requires-Dist: cachecontrol[filecache] (>=0.12.4,<0.13.0)
Requires-Dist: cachy (>=0.3.0,<0.4.0)
Requires-Dist: cleo (>=1.0.0a4,<2.0.0)
Requires-Dist: crashtest (>=0.3.0,<0.4.0)
Requires-Dist: dataclasses (>=0.8,<0.9); python_version >= "3.6" and python_version < "3.7"
Requires-Dist: entrypoints (>=0.3,<0.4)
Requires-Dist: html5lib (>=1.0,<2.0)
Requires-Dist: importlib-metadata (>=1.6.0,<2.0.0); python_version < "3.8"
Requires-Dist: keyring (>=21.2.0)
Requires-Dist: packaging (>=20.4,<21.0)
Requires-Dist: pexpect (>=4.7.0,<5.0.0)
Requires-Dist: pkginfo (>=1.5,<2.0)
Requires-Dist: pkm-buildsys (>=0.2.2,<0.3.0)
Requires-Dist: protopy-lib (>=0.2.0)
Requires-Dist: requests (>=2.18,<3.0)
Requires-Dist: requests-toolbelt (>=0.9.1,<0.10.0)
Requires-Dist: shellingham (>=1.1,<2.0)
Requires-Dist: typing-extensions (>=3.10.0.2,<4.0.0.0)
Requires-Dist: virtualenv
Project-URL: Documentation, https://github.com/bennylut/relaxed-poetry
Project-URL: Repository, https://github.com/bennylut/relaxed-poetry
